tdim/__init__.py
tdim/__main__.py
tdim/py.typed
tdim-0.3.0.dist-info/METADATA
tdim-0.3.0.dist-info/WHEEL
tdim-0.3.0.dist-info/entry_points.txt
tdim-0.3.0.dist-info/top_level.txt
tdim-0.3.0.dist-info/RECORD
