Metadata-Version: 2.1
Name: tdim
Version: 0.3.0
Summary: A simple tool for displaying terminal dimensions
Home-page: https://github.com/davep/tdim
Author: Dave Pearson
Author-email: davep@davep.org
Maintainer: Dave Pearson
Maintainer-email: davep@davep.org
License: License :: OSI Approved :: GNU General Public License v3 or later (GPLv3+)
Project-URL: Documentation, https://github.com/davep/tdim/blob/main/README.md
Project-URL: Source, https://github.com/davep/tdim
Project-URL: Issues, https://github.com/davep/tdim/issues
Project-URL: Discussions, https://github.com/davep/tdim/discussions
Keywords: terminal
Classifier: License :: OSI Approved :: GNU General Public License v3 or later (GPLv3+)
Classifier: Environment :: Console
Classifier: Development Status :: 3 - Alpha
Classifier: Intended Audience :: Developers
Classifier: Operating System :: OS Independent
Classifier: Programming Language :: Python :: 3.8
Classifier: Programming Language :: Python :: 3.9
Classifier: Programming Language :: Python :: 3.10
Classifier: Programming Language :: Python :: 3.11
Classifier: Programming Language :: Python :: 3.12
Classifier: Topic :: Terminals
Classifier: Typing :: Typed
Requires-Python: >=3.8
Requires-Dist: textual >=0.52.1
